{"book": "Obadiah", "chapters": {"1": {"1": [["ὅρασις", "ὅρασις", "N.NSF"], ["Αβδιου", "Αβδιας", "N.GSM"], ["τάδε", "ὅδε", "RD.APN"], ["λέγει", "λέγω", "V.PAI3S"], ["κύριος", "κύριος", "N.NSM"], ["ὁ", "ὁ", "RA.NSM"], ["θεὸς", "θεός", "N.NSM"], ["τῇ", "ὁ", "RA.DSF"], ["Ιδουμαίᾳ", "Ἰδουμαία", "N.DSF"], ["ἀκοὴν", "ἀκοή", "N.ASF"], ["ἤκουσα", "ἀκούω", "V.AAI1S"], ["παρὰ", "παρά", "P"], ["κυρίου", "κύριος", "N.GSM"], ["καὶ", "καί", "C"], ["περιοχὴν", "περιοχή", "N.ASF"], ["εἰς", "εἰς", "P"], ["τὰ", "ὁ", "RA.APN"], ["ἔθνη", "ἔθνος", "N.APN"], ["ἐξαπέστειλεν", "ἐξαποστέλλω", "V.AAI3S"], ["ἀνάστητε", "ἀνίστημι", "V.AAD2P"], ["καὶ", "καί", "C"], ["ἐξαναστῶμεν", "ἐξανίστημι", "V.AAS1P"], ["ἐπ᾿", "ἐπί", "P"], ["αὐτὴν", "αὐτός", "RD.ASF"], ["εἰς", "εἰς", "P"], ["πόλεμον", "πόλεμος", "N.ASM"]], "2": [["ἰδοὺ", "ἰδού", "I"], ["ὀλιγοστὸν", "ὀλιγοστός", "A.ASM"], ["δέδωκά", "δίδωμι", "V.XAI1S"], ["σε", "σέ", "RP.AS"], ["ἐν", "ἐν", "P"], ["τοῖς", "ὁ", "RA.DPN"], ["ἔθνεσιν", "ἔθνος", "N.DPN"], ["ἠτιμωμένος", "ἀτιμόω", "V.XPPNSM"], ["σὺ", "σύ", "RP.NS"], ["εἶ", "εἰμί", "V.PAI2S"], ["σφόδρα", "σφόδρα", "D"]], "3": [["ὑπερηφανία", "ὑπερηφανία", "N.NSF"], ["τῆς", "ὁ", "RA.GSF"], ["καρδίας", "καρδία", "N.GSF"], ["σου", "σοῦ", "RP.GS"], ["ἐπῆρέν", "ἐπαίρω", "V.AAI3S"], ["σε", "σέ", "RP.AS"], ["κατασκηνοῦντα", "κατασκηνόω", "V.PAPASM"], ["ἐν", "ἐν", "P"], ["ταῖς", "ὁ", "RA.DPF"], ["ὀπαῖς", "ὀπή", "N.DPF"], ["τῶν", "ὁ", "RA.GPM"], ["πετρῶν", "πέτρος", "N.GPM"], ["ὑψῶν", "ὕψος", "N.GPN"], ["κατοικίαν", "κατοικία", "N.ASF"], ["αὐτοῦ", "αὐτός", "RD.GSM"], ["λέγων", "λέγω", "V.PAPNSM"], ["ἐν", "ἐν", "P"], ["καρδίᾳ", "καρδία", "N.DSF"], ["αὐτοῦ", "αὐτός", "RD.GSM"], ["τίς", "τίς", "RI.NSM"], ["με", "μέ", "RP.AS"], ["κατάξει", "κατάγω", "V.FAI3S"], ["ἐπὶ", "ἐπί", "P"], ["τὴν", "ὁ", "RA.ASF"], ["γῆν", "γῆ", "N.ASF"]], "4": [["ἐὰν", "ἐάν", "C"], ["μετεωρισθῇς", "μετεωρίζω", "V.APS2S"], ["ὡς", "ὥς", "C"], ["ἀετὸς", "ἀετός", "N.NSM"], ["καὶ", "καί", "C"], ["ἐὰν", "ἐάν", "C"], ["ἀνὰ", "ἀνά", "P"], ["μέσον", "μέσος", "A.ASN"], ["τῶν", "ὁ", "RA.GPN"], ["ἄστρων", "ἄστρον", "N.GPN"], ["θῇς", "τίθημι", "V.AAS2S"], ["νοσσιάν", "νοσσιά", "N.ASF"], ["σου", "σοῦ", "RP.GS"], ["ἐκεῖθεν", "ἐκεῖθεν", "D"], ["κατάξω", "κατάγω", "V.FAI1S"], ["σε", "σέ", "RP.AS"], ["λέγει", "λέγω", "V.PAI3S"], ["κύριος", "κύριος", "N.NSM"]], "5": [["εἰ", "εἰ", "C"], ["κλέπται", "κλέπτης", "N.NPM"], ["εἰσῆλθον", "εἰσέρχομαι", "V.AAI3P"], ["πρὸς", "πρός", "P"], ["σὲ", "σέ", "RP.AS"], ["ἢ", "ἤ", "C"], ["λῃσταὶ", "λῃστής", "N.NPM"], ["νυκτός", "νύξ", "N.GSF"], ["ποῦ", "ποῦ", "D"], ["ἂν", "ἄν", "X"], ["ἀπερρίφης", "ἀπορρίπτω", "V.API2S"], ["οὐκ", "οὐ", "D"], ["ἂν", "ἄν", "X"], ["ἔκλεψαν", "κλέπτω", "V.AAI3P"], ["τὰ", "ὁ", "RA.APN"], ["ἱκανὰ", "ἱκανός", "A.APN"], ["ἑαυτοῖς", "ἑαυτοῦ", "RD.DPM"], ["καὶ", "καί", "C"], ["εἰ", "εἰ", "C"], ["τρυγηταὶ", "τρυγητής", "N.NPM"], ["εἰσῆλθον", "εἰσέρχομαι", "V.AAI3P"], ["πρὸς", "πρός", "P"], ["σέ", "σέ", "RP.AS"], ["οὐκ", "οὐ", "D"], ["ἂν", "ἄν", "X"], ["ὑπελίποντο", "ὑπολείπω", "V.AMI3P"], ["ἐπιφυλλίδα", "ἐπιφυλλίς", "N.ASF"]], "6": [["πῶς", "πῶς", "D"], ["ἐξηρευνήθη", "ἐξερευνάω", "V.API3S"], ["Ησαυ", "Ἠσαῦ", "N.NSM"], ["καὶ", "καί", "C"], ["κατελήμφθη", "καταλαμβάνω", "V.API3S"], ["αὐτοῦ", "αὐτός", "RD.GSM"], ["τὰ", "ὁ", "RA.NPN"], ["κεκρυμμένα", "κρύπτω", "V.XMPNPN"]], "7": [["ἕως", "ἕως", "P"], ["τῶν", "ὁ", "RA.GPN"], ["ὁρίων", "ὅριον", "N.GPN"], ["σου", "σοῦ", "RP.GS"], ["ἐξαπέστειλάν", "ἐξαποστέλλω", "V.AAI3P"], ["σε", "σέ", "RP.AS"], ["πάντες", "πᾶς", "A.NPM"], ["οἱ", "ὁ", "RA.NPM"], ["ἄνδρες", "ἀνήρ", "N.NPM"], ["τῆς", "ὁ", "RA.GSF"], ["διαθήκης", "διαθήκη", "N.GSF"], ["σου", "σοῦ", "RP.GS"], ["ἀντέστησάν", "ἀνθίστημι", "V.AAI3P"], ["σοι", "σοί", "RP.DS"], ["ἠδυνάσθησαν", "δύναμαι", "V.API3P"], ["πρὸς", "πρός", "P"], ["σὲ", "σέ", "RP.AS"], ["ἄνδρες", "ἀνήρ", "N.NPM"], ["εἰρηνικοί", "εἰρηνικός", "A.NPM"], ["σου", "σοῦ", "RP.GS"], ["ἔθηκαν", "τίθημι", "V.AAI3P"], ["ἔνεδρα", "ἔνεδρον", "N.APN"], ["ὑποκάτω", "ὑποκάτω", "P"], ["σου", "σοῦ", "RP.GS"], ["οὐκ", "οὐ", "D"], ["ἔστιν", "εἰμί", "V.PAI3S"], ["σύνεσις", "σύνεσις", "N.NSF"], ["αὐτοῖς", "αὐτός", "RD.DPM"]], "8": [["ἐν", "ἐν", "P"], ["ἐκείνῃ", "ἐκεῖνος", "RD.DSF"], ["τῇ", "ὁ", "RA.DSF"], ["ἡμέρᾳ", "ἡμέρα", "N.DSF"], ["λέγει", "λέγω", "V.PAI3S"], ["κύριος", "κύριος", "N.NSM"], ["ἀπολῶ", "ἀπόλλυμι", "V.FAI1S"], ["σοφοὺς", "σοφός", "A.APM"], ["ἐκ", "ἐκ", "P"], ["τῆς", "ὁ", "RA.GSF"], ["Ιδουμαίας", "Ἰδουμαία", "N.GSF"], ["καὶ", "καί", "C"], ["σύνεσιν", "σύνεσις", "N.ASF"], ["ἐξ", "ἐκ", "P"], ["ὄρους", "ὄρος", "N.GSN"], ["Ησαυ", "Ἠσαῦ", "N.GSM"]], "9": [["καὶ", "καί", "C"], ["πτοηθήσονται", "πτοέω", "V.FPI3P"], ["οἱ", "ὁ", "RA.NPM"], ["μαχηταί", "μαχητής", "N.NPM"], ["σου", "σοῦ", "RP.GS"], ["οἱ", "ὁ", "RA.NPM"], ["ἐκ", "ἐκ", "P"], ["Θαιμαν", "Θαιμάν", "N.GS"], ["ὅπως", "ὅπως", "C"], ["ἐξαρθῇ", "ἐξαίρω", "V.APS3S"], ["ἄνθρωπος", "ἄνθρωπος", "N.NSM"], ["ἐξ", "ἐκ", "P"], ["ὄρους", "ὄρος", "N.GSN"], ["Ησαυ", "Ἠσαῦ", "N.GSM"]], "10": [["διὰ", "διά", "P"], ["τὴν", "ὁ", "RA.ASF"], ["σφαγὴν", "σφαγή", "N.ASF"], ["καὶ", "καί", "C"], ["τὴν", "ὁ", "RA.ASF"], ["ἀσέβειαν", "ἀσέβεια", "N.ASF"], ["τὴν", "ὁ", "RA.ASF"], ["εἰς", "εἰς", "P"], ["τὸν", "ὁ", "RA.ASM"], ["ἀδελφόν", "ἀδελφός", "N.ASM"], ["σου", "σοῦ", "RP.GS"], ["Ιακωβ", "Ἰακώβ", "N.ASM"], ["καὶ", "καί", "C"], ["καλύψει", "καλύπτω", "V.FAI3S"], ["σε", "σέ", "RP.AS"], ["αἰσχύνη", "αἰσχύνη", "N.NSF"], ["καὶ", "καί", "C"], ["ἐξαρθήσῃ", "ἐξαίρω", "V.FPI2S"], ["εἰς", "εἰς", "P"], ["τὸν", "ὁ", "RA.ASM"], ["αἰῶνα", "αἰών", "N.ASM"]], "11": [["ἀφ᾿", "ἀπό", "P"], ["ἧς", "ὅς", "RR.GSF"], ["ἡμέρας", "ἡμέρα", "N.GSF"], ["ἀντέστης", "ἀνθίστημι", "V.AAI2S"], ["ἐξ", "ἐκ", "P"], ["ἐναντίας", "ἐναντίος", "A.GSF"], ["ἐν", "ἐν", "P"], ["ἡμέρᾳ", "ἡμέρα", "N.DSF"], ["αἰχμαλωτευόντων", "αἰχμαλωτεύω", "V.PAPGPM"], ["ἀλλογενῶν", "ἀλλογενής", "A.GPM"], ["δύναμιν", "δύναμις", "N.ASF"], ["αὐτοῦ", "αὐτός", "RD.GSM"], ["καὶ", "καί", "C"], ["ἀλλότριοι", "ἀλλότριος", "A.NPM"], ["εἰσῆλθον", "εἰσέρχομαι", "V.AAI3P"], ["εἰς", "εἰς", "P"], ["πύλας", "πύλη", "N.APF"], ["αὐτοῦ", "αὐτός", "RD.GSM"], ["καὶ", "καί", "C"], ["ἐπὶ", "ἐπί", "P"], ["Ιερουσαλημ", "Ἱερουσαλήμ", "N.ASF"], ["ἔβαλον", "βάλλω", "V.AAI3P"], ["κλήρους", "κλῆρος", "N.APM"], ["καὶ", "καί", "C"], ["σὺ", "σύ", "RP.NS"], ["ἦς", "εἰμί", "V.IAI2S"], ["ὡς", "ὥς", "C"], ["εἷς", "εἷς", "A.NSM"], ["ἐξ", "ἐκ", "P"], ["αὐτῶν", "αὐτός", "RD.GPM"]], "12": [["καὶ", "καί", "C"], ["μὴ", "μή", "D"], ["ἐπίδῃς", "ἐπιδέω", "V.PAS2S"], ["ἡμέραν", "ἡμέρα", "N.ASF"], ["ἀδελφοῦ", "ἀδελφός", "N.GSM"], ["σου", "σοῦ", "RP.GS"], ["ἐν", "ἐν", "P"], ["ἡμέρᾳ", "ἡμέρα", "N.DSF"], ["ἀλλοτρίων", "ἀλλότριος", "A.GPM"], ["καὶ", "καί", "C"], ["μὴ", "μή", "D"], ["ἐπιχαρῇς", "ἐπιχαίρω", "V.APS2S"], ["ἐπὶ", "ἐπί", "P"], ["τοὺς", "ὁ", "RA.APM"], ["υἱοὺς", "υἱός", "N.APM"], ["Ιουδα", "Ἰουδά", "N.GSM"], ["ἐν", "ἐν", "P"], ["ἡμέρᾳ", "ἡμέρα", "N.DSF"], ["ἀπωλείας", "ἀπώλεια", "N.GSF"], ["αὐτῶν", "αὐτός", "RD.GPM"], ["καὶ", "καί", "C"], ["μὴ", "μή", "D"], ["μεγαλορρημονήσῃς", "μεγαλορρημονέω", "V.AAS2S"], ["ἐν", "ἐν", "P"], ["ἡμέρᾳ", "ἡμέρα", "N.DSF"], ["θλίψεως", "θλῖψις", "N.GSF"]], "13": [["μηδὲ", "μηδέ", "C"], ["εἰσέλθῃς", "εἰσέρχομαι", "V.AAS2S"], ["εἰς", "εἰς", "P"], ["πύλας", "πύλη", "N.APF"], ["λαῶν", "λαός", "N.GPM"], ["ἐν", "ἐν", "P"], ["ἡμέρᾳ", "ἡμέρα", "N.DSF"], ["πόνων", "πόνος", "N.GPM"], ["αὐτῶν", "αὐτός", "RD.GPM"], ["μηδὲ", "μηδέ", "C"], ["ἐπίδῃς", "ἐπιδέω", "V.PAS2S"], ["καὶ", "καί", "C"], ["σὺ", "σύ", "RP.NS"], ["τὴν", "ὁ", "RA.ASF"], ["συναγωγὴν", "συναγωγή", "N.ASF"], ["αὐτῶν", "αὐτός", "RD.GPM"], ["ἐν", "ἐν", "P"], ["ἡμέρᾳ", "ἡμέρα", "N.DSF"], ["ὀλέθρου", "ὄλεθρος", "N.GSM"], ["αὐτῶν", "αὐτός", "RD.GPM"], ["μηδὲ", "μηδέ", "C"], ["συνεπιθῇ", "συνεπιτίθημι", "V.AAS3S"], ["ἐπὶ", "ἐπί", "P"], ["τὴν", "ὁ", "RA.ASF"], ["δύναμιν", "δύναμις", "N.ASF"], ["αὐτῶν", "αὐτός", "RD.GPM"], ["ἐν", "ἐν", "P"], ["ἡμέρᾳ", "ἡμέρα", "N.DSF"], ["ἀπωλείας", "ἀπώλεια", "N.GSF"], ["αὐτῶν", "αὐτός", "RD.GPM"]], "14": [["μηδὲ", "μηδέ", "C"], ["ἐπιστῇς", "ἐφίστημι", "V.AAS2S"], ["ἐπὶ", "ἐπί", "P"], ["τὰς", "ὁ", "RA.APF"], ["διεκβολὰς", "διεκβολή", "N.APF"], ["αὐτῶν", "αὐτός", "RD.GPM"], ["τοῦ", "ὁ", "RA.GSN"], ["ἐξολεθρεῦσαι", "ἐξολοθρεύω", "V.AAN"], ["τοὺς", "ὁ", "RA.APM"], ["ἀνασῳζομένους", "ἀνασώζω", "V.PMPAPM"], ["αὐτῶν", "αὐτός", "RD.GPM"], ["μηδὲ", "μηδέ", "C"], ["συγκλείσῃς", "συγκλείω", "V.AAS2S"], ["τοὺς", "ὁ", "RA.APM"], ["φεύγοντας", "φεύγω", "V.PAPAPM"], ["ἐξ", "ἐκ", "P"], ["αὐτῶν", "αὐτός", "RD.GPM"], ["ἐν", "ἐν", "P"], ["ἡμέρᾳ", "ἡμέρα", "N.DSF"], ["θλίψεως", "θλῖψις", "N.GSF"]], "15": [["διότι", "διότι", "C"], ["ἐγγὺς", "ἐγγύς", "D"], ["ἡμέρα", "ἡμέρα", "N.NSF"], ["κυρίου", "κύριος", "N.GSM"], ["ἐπὶ", "ἐπί", "P"], ["πάντα", "πᾶς", "A.APN"], ["τὰ", "ὁ", "RA.APN"], ["ἔθνη", "ἔθνος", "N.APN"], ["ὃν", "ὅς", "RR.ASM"], ["τρόπον", "τρόπος", "N.ASM"], ["ἐποίησας", "ποιέω", "V.AAI2S"], ["οὕτως", "οὕτως", "D"], ["ἔσται", "εἰμί", "V.FMI3S"], ["σοι", "σοί", "RP.DS"], ["τὸ", "ὁ", "RA.NSN"], ["ἀνταπόδομά", "ἀνταπόδομα", "N.NSN"], ["σου", "σοῦ", "RP.GS"], ["ἀνταποδοθήσεται", "ἀνταποδίδωμι", "V.FPI3S"], ["εἰς", "εἰς", "P"], ["κεφαλήν", "κεφαλή", "N.ASF"], ["σου", "σοῦ", "RP.GS"]], "16": [["διότι", "διότι", "C"], ["ὃν", "ὅς", "RR.ASM"], ["τρόπον", "τρόπος", "N.ASM"], ["ἔπιες", "πίνω", "V.AAI2S"], ["ἐπὶ", "ἐπί", "P"], ["τὸ", "ὁ", "RA.ASN"], ["ὄρος", "ὄρος", "N.ASN"], ["τὸ", "ὁ", "RA.ASN"], ["ἅγιόν", "ἅγιος", "A.ASN"], ["μου", "μου", "RP.GS"], ["πίονται", "πίνω", "V.FMI3P"], ["πάντα", "πᾶς", "A.NPN"], ["τὰ", "ὁ", "RA.NPN"], ["ἔθνη", "ἔθνος", "N.NPN"], ["οἶνον", "οἶνος", "N.ASM"], ["πίονται", "πίνω", "V.FMI3P"], ["καὶ", "καί", "C"], ["καταβήσονται", "καταβαίνω", "V.FMI3P"], ["καὶ", "καί", "C"], ["ἔσονται", "εἰμί", "V.FMI3P"], ["καθὼς", "καθώς", "D"], ["οὐχ", "οὐ", "D"], ["ὑπάρχοντες", "ὑπάρχοντα", "V.PAPNPM"]], "17": [["ἐν", "ἐν", "P"], ["δὲ", "δέ", "X"], ["τῷ", "ὁ", "RA.DSN"], ["ὄρει", "ὄρος", "N.DSN"], ["Σιων", "Σιών", "N.GS"], ["ἔσται", "εἰμί", "V.FMI3S"], ["ἡ", "ὁ", "RA.NSF"], ["σωτηρία", "σωτηρία", "N.NSF"], ["καὶ", "καί", "C"], ["ἔσται", "εἰμί", "V.FMI3S"], ["ἅγιον", "ἅγιος", "A.NSN"], ["καὶ", "καί", "C"], ["κατακληρονομήσουσιν", "κατακληρονομέω", "V.FAI3P"], ["ὁ", "ὁ", "RA.NSM"], ["οἶκος", "οἶκος", "N.NSM"], ["Ιακωβ", "Ἰακώβ", "N.GSM"], ["τοὺς", "ὁ", "RA.APM"], ["κατακληρονομήσαντας", "κατακληρονομέω", "V.AAPAPM"], ["αὐτούς", "αὐτός", "RD.APM"]], "18": [["καὶ", "καί", "C"], ["ἔσται", "εἰμί", "V.FMI3S"], ["ὁ", "ὁ", "RA.NSM"], ["οἶκος", "οἶκος", "N.NSM"], ["Ιακωβ", "Ἰακώβ", "N.GSM"], ["πῦρ", "πῦρ", "N.NSN"], ["ὁ", "ὁ", "RA.NSM"], ["δὲ", "δέ", "X"], ["οἶκος", "οἶκος", "N.NSM"], ["Ιωσηφ", "Ἰωσήφ", "N.GSM"], ["φλόξ", "φλόξ", "N.NSF"], ["ὁ", "ὁ", "RA.NSM"], ["δὲ", "δέ", "X"], ["οἶκος", "οἶκος", "N.NSM"], ["Ησαυ", "Ἠσαῦ", "N.GSM"], ["εἰς", "εἰς", "P"], ["καλάμην", "καλάμη", "N.ASF"], ["καὶ", "καί", "C"], ["ἐκκαυθήσονται", "ἐκκαίω", "V.FPI3P"], ["εἰς", "εἰς", "P"], ["αὐτοὺς", "αὐτός", "RD.APM"], ["καὶ", "καί", "C"], ["καταφάγονται", "κατεσθίω", "V.FMI3P"], ["αὐτούς", "αὐτός", "RD.APM"], ["καὶ", "καί", "C"], ["οὐκ", "οὐ", "D"], ["ἔσται", "εἰμί", "V.FMI3S"], ["πυροφόρος", "πυροφόρος", "A.NSM"], ["ἐν", "ἐν", "P"], ["τῷ", "ὁ", "RA.DSM"], ["οἴκῳ", "οἶκος", "N.DSM"], ["Ησαυ", "Ἠσαῦ", "N.GSM"], ["διότι", "διότι", "C"], ["κύριος", "κύριος", "N.NSM"], ["ἐλάλησεν", "λαλέω", "V.AAI3S"]], "19": [["καὶ", "καί", "C"], ["κατακληρονομήσουσιν", "κατακληρονομέω", "V.FAI3P"], ["οἱ", "ὁ", "RA.NPM"], ["ἐν", "ἐν", "P"], ["Ναγεβ", "Ναγεβ", "N.DS"], ["τὸ", "ὁ", "RA.ASN"], ["ὄρος", "ὄρος", "N.ASN"], ["τὸ", "ὁ", "RA.ASN"], ["Ησαυ", "Ἠσαῦ", "N.ASN"], ["καὶ", "καί", "C"], ["οἱ", "ὁ", "RA.NPM"], ["ἐν", "ἐν", "P"], ["τῇ", "ὁ", "RA.DSF"], ["Σεφηλα", "Σεφηλα", "N.DSF"], ["τοὺς", "ὁ", "RA.APM"], ["ἀλλοφύλους", "ἀλλόφυλος", "A.APM"], ["καὶ", "καί", "C"], ["κατακληρονομήσουσιν", "κατακληρονομέω", "V.FAI3P"], ["τὸ", "ὁ", "RA.ASN"], ["ὄρος", "ὄρος", "N.ASN"], ["Εφραιμ", "Ἐφραίμ", "N.GSM"], ["καὶ", "καί", "C"], ["τὸ", "ὁ", "RA.ASN"], ["πεδίον", "πεδίον", "N.ASN"], ["Σαμαρείας", "Σαμάρεια", "N.GSF"], ["καὶ", "καί", "C"], ["Βενιαμιν", "Βενιαμίν", "N.ASM"], ["καὶ", "καί", "C"], ["τὴν", "ὁ", "RA.ASF"], ["Γαλααδῖτιν", "Γαλααδῖτις", "N.ASF"]], "20": [["καὶ", "καί", "C"], ["τῆς", "ὁ", "RA.GSF"], ["μετοικεσίας", "μετοικεσία", "N.GSF"], ["ἡ", "ὁ", "RA.NSF"], ["ἀρχὴ", "ἀρχή", "N.NSF"], ["αὕτη", "οὗτος", "RD.NSF"], ["τοῖς", "ὁ", "RA.DPM"], ["υἱοῖς", "υἱός", "N.DPM"], ["Ισραηλ", "Ἰσραήλ", "N.GSM"], ["γῆ", "γῆ", "N.NSF"], ["τῶν", "ὁ", "RA.GPM"], ["Χαναναίων", "Χαναναῖος", "N.GPM"], ["ἕως", "ἕως", "P"], ["Σαρεπτων", "Σάρεπτα", "N.GPF"], ["καὶ", "καί", "C"], ["ἡ", "ὁ", "RA.NSF"], ["μετοικεσία", "μετοικεσία", "N.NSF"], ["Ιερουσαλημ", "Ἱερουσαλήμ", "N.GSF"], ["ἕως", "ἕως", "P"], ["Εφραθα", "Εφραθα", "N.GS"], ["καὶ", "καί", "C"], ["κληρονομήσουσιν", "κληρονομέω", "V.FAI3P"], ["τὰς", "ὁ", "RA.APF"], ["πόλεις", "πόλις", "N.APF"], ["τοῦ", "ὁ", "RA.GSM"], ["Ναγεβ", "Ναγεβ", "N.GS"]], "21": [["καὶ", "καί", "C"], ["ἀναβήσονται", "ἀναβαίνω", "V.FMI3P"], ["ἄνδρες", "ἀνήρ", "N.NPM"], ["σεσῳσμένοι", "σώζω", "V.XPPNPM"], ["ἐξ", "ἐκ", "P"], ["ὄρους", "ὄρος", "N.GSN"], ["Σιων", "Σιών", "N.GS"], ["τοῦ", "ὁ", "RA.GSN"], ["ἐκδικῆσαι", "ἐκδικέω", "V.AAN"], ["τὸ", "ὁ", "RA.ASN"], ["ὄρος", "ὄρος", "N.ASN"], ["Ησαυ", "Ἠσαῦ", "N.GSM"], ["καὶ", "καί", "C"], ["ἔσται", "εἰμί", "V.FMI3S"], ["τῷ", "ὁ", "RA.DSM"], ["κυρίῳ", "κύριος", "N.DSM"], ["ἡ", "ὁ", "RA.NSF"], ["βασιλεία", "βασιλεία", "N.NSF"]]}}}