{
  "id": "ws_045",
  "title": "Parables of Jesus \u2014 Medium #5",
  "theme": "Parables of Jesus",
  "difficulty": "Medium",
  "gridSize": 15,
  "grid": [
    "SNIGRIVNETXRSJZ",
    "CFDRAYENIVVOLKF",
    "UIQCMAFFJJPDOAE",
    "NATIRAMASDOOGRQ",
    "MDDEEDWBPJMAUKM",
    "SSTPRODIGALSONB",
    "OGUFYNOKICAUXQR",
    "PIARDEWGLEIULOX",
    "JAULSTQSRYKSIYA",
    "GRFZTSWTOMFQWCG",
    "LMUBNWFDTWGFEOQ",
    "RLGLECSXLFEKSIR",
    "AFRELIFKKIFRJFE",
    "EJKKATWEFLDNJHO",
    "PMUSTARDSEEDBYS"
  ],
  "words": [
    "SOWER",
    "MUSTARDSEED",
    "PRODIGALSON",
    "TALENTS",
    "NET",
    "PEARL",
    "GOODSAMARITAN",
    "TENVIRGINS",
    "TREASURE",
    "VINEYARD"
  ]
}