{
  "id": "ws_052",
  "title": "Teachings of Jesus \u2014 Medium #2",
  "theme": "Teachings of Jesus",
  "difficulty": "Medium",
  "gridSize": 15,
  "grid": [
    "WNSCIAJXEFRCKZW",
    "KREYZGDPEFWMGWE",
    "FEREVIGROFGNBCA",
    "QYVLRJKLZNIDZAG",
    "MAAYKIOBCTVGCBW",
    "FRNEIVDDSTCHFCF",
    "BPTKEYTAIGHRNRC",
    "HKSCRRFPZSAFOQM",
    "QOSEGVOXSECOBSI",
    "HUSHKINGDOMIVNS",
    "LILFMTLYTGKFPTG",
    "RJLACENCWXNRPLS",
    "OQCIYHRTIDTZFXE",
    "AYNTDUUCMUZXXGV",
    "FJFHMNYPYLMYRAZ"
  ],
  "words": [
    "KINGDOM",
    "DISCIPLE",
    "FORGIVE",
    "PRAYER",
    "FASTING",
    "SERVANT",
    "CROSS",
    "LOVE",
    "FAITH",
    "MERCY"
  ]
}