{
  "id": "ws_118",
  "title": "Psalms \u2014 Medium #8",
  "theme": "Psalms",
  "difficulty": "Medium",
  "gridSize": 15,
  "grid": [
    "GKNIGAUFCNMUETN",
    "NNVDBMAHEGWSOCE",
    "IAOWIPDXLFISIYZ",
    "SIFIPCHOIRMJQLJ",
    "GGXJZRQEGUFEREN",
    "ZJPPRAHFLXGQXFV",
    "MZTHANKSGIVINGY",
    "EMUDYECOGDQVIKN",
    "RVUWSFPQRGQWVOZ",
    "CKGEFRBSEDTOLJV",
    "YYRJLYISTGERAGR",
    "KTESIARPLOKSTXH",
    "XJWQTWDMEHAHEXU",
    "OXRUEBOBHGHILFZ",
    "ZHLLBZYASWWPVQL"
  ],
  "words": [
    "PRAISE",
    "WORSHIP",
    "SING",
    "HARP",
    "MERCY",
    "REFUGE",
    "SHELTER",
    "THANKSGIVING",
    "ZION",
    "CHOIR"
  ]
}