{
  "id": "ws_236",
  "title": "Christian Living \u2014 Hard #6",
  "theme": "Christian Living",
  "difficulty": "Hard",
  "gridSize": 20,
  "grid": [
    "SSOHZTTRVBBYESNATLBN",
    "RXSWOEHPDRDZTTKASQZK",
    "ECNEITAPRABMFIHICBGS",
    "QRQPNPWXRCTGWHRQIUBY",
    "XWNIAEGLYTVTRBVACDPO",
    "YUEBVWVWFHMLYFNTHKHN",
    "YJECWOIIQHTTRMOTZCYN",
    "FXLSIPTUGYEMGVKICTBH",
    "MVSYKVYGYRQREYDQIHHT",
    "TYIKTWRTLDOTPVOROFLI",
    "WVYNCDMEDZHFOJUWDPSA",
    "FVCEWCXESJSZHPFQWGUF",
    "HXKOCPYCEYGDUSBJUDTB",
    "RYXSMWOAPKLWDCRUJMZZ",
    "XJJQYVJPPHNOHCERNYCV",
    "BEKUDDSWYNBEVLYLWQSB",
    "AXDJCDKMOCWZSEAOQFTX",
    "VOCACUMVXPHHYSRXSWCM",
    "LFKFVXGEYCMUGMPTSAVH",
    "TPTTTPWEOLYRFNPIJAIB"
  ],
  "words": [
    "LOVE",
    "HOPE",
    "FAITH",
    "PRAYER",
    "SERVICE",
    "FORGIVENESS",
    "PURITY",
    "MEEKNESS",
    "PATIENCE",
    "CHARITY"
  ]
}